ZNLP/__init__.py
ZNLP/lemmatizer.py
ZNLP/metrics.py
ZNLP/ner.py
ZNLP/parser.py
ZNLP/pos_tagger.py
ZNLP/text_classifier.py
ZNLP/tokenizer.py
zetnlp-1.0.0.dist-info/licenses/LICENSE
zetnlp-1.0.0.dist-info/METADATA
zetnlp-1.0.0.dist-info/WHEEL
zetnlp-1.0.0.dist-info/top_level.txt
zetnlp-1.0.0.dist-info/RECORD
