Metadata-Version: 2.4
Name: zetnlp
Version: 1.0.0
Home-page: https://github.com/prasenjeett/ZetNLP
Author: Prasenjeet Howlader
Author-email: prasenjeethowlader122@gmail.com
License: MIT
Classifier: Programming Language :: Python :: 3
Classifier: License :: OSI Approved :: MIT License
Classifier: Operating System :: OS Independent
License-File: LICENSE
Requires-Dist: numpy
Requires-Dist: nltk
Requires-Dist: spacy
Dynamic: author
Dynamic: author-email
Dynamic: classifier
Dynamic: description
Dynamic: description-content-type
Dynamic: home-page
Dynamic: license
Dynamic: license-file
Dynamic: requires-dist
